querent/__init__.py
querent/callback/__init__.py
querent/callback/event_callback_dispatcher.py
querent/callback/event_callback_interface.py
querent/channel/__init__.py
querent/channel/channel_interface.py
querent/cli/__init__.py
querent/collectors/__init__.py
querent/collectors/collector_base.py
querent/collectors/collector_errors.py
querent/collectors/collector_factory.py
querent/collectors/collector_resolver.py
querent/collectors/aws/__init__.py
querent/collectors/aws/aws_collector.py
querent/collectors/azure/__init__.py
querent/collectors/azure/azure_collector.py
querent/collectors/drive/__init__.py
querent/collectors/drive/google_drive_collector.py
querent/collectors/dropbox/__init__.py
querent/collectors/dropbox/dropbox_collector.py
querent/collectors/email/__init__.py
querent/collectors/email/email_collector.py
querent/collectors/email/imap.py
querent/collectors/fs/__init__.py
querent/collectors/fs/fs_collector.py
querent/collectors/gcs/__init__.py
querent/collectors/gcs/gcs_collector.py
querent/collectors/github/__init__.py
querent/collectors/github/github_collector.py
querent/collectors/jira/__init__.py
querent/collectors/jira/jira_collector.py
querent/collectors/news/__init__.py
querent/collectors/news/news_collector.py
querent/collectors/slack/__init__.py
querent/collectors/slack/slack_collector.py
querent/collectors/webscaper/__init__.py
querent/collectors/webscaper/web_scraper_collector.py
querent/common/__init__.py
querent/common/common_errors.py
querent/common/uri.py
querent/common/errors/__init__.py
querent/common/errors/metric_errors.py
querent/common/types/__init__.py
querent/common/types/collected_bytes.py
querent/common/types/collector_config_keys.py
querent/common/types/config_keys.py
querent/common/types/engine_config_keys.py
querent/common/types/file_buffer.py
querent/common/types/ingested_code.py
querent/common/types/ingested_images.py
querent/common/types/ingested_messages.py
querent/common/types/ingested_table.py
querent-3.1.2.dist-info/LICENCE
querent-3.1.2.dist-info/METADATA
querent-3.1.2.dist-info/WHEEL
querent-3.1.2.dist-info/top_level.txt
querent-3.1.2.dist-info/RECORD
