Metadata-Version: 2.1
Name: querent
Version: 3.1.2
Summary: The Asynchronous Data Dynamo and Graph Neural Network Catalyst
Home-page: https://github.com/Querent-ai/querent-ai
Author: Querent AI
License: Business Source License 1.1
Project-URL: Documentation, https://github.com/Querent-ai/querent-ai/docs
Project-URL: Issue Tracker, https://github.com/Querent-ai/querent-ai/issues
Keywords: Graph Neural Network,Scalability,Data-Driven Insights,GNN,Async,Knowledge Graphs,KG,Large Language Models,asyncio,Insights,aysnchronous,LLM,transformers,pytorch,Llama-index,AI,Artificial Intelligence,Neo4j,Queues,QuiAssisstant,Collectors,Data,Data Science,Data Engineering,Data Analysis,Data Analytics,News,NLP,Natural Language Processing,Text,Text Analysis,Deep Learning,Graphs,Graph Theory,Graph Algorithms,Graph Analytics,Graph Databases,Graph Processing,Graph Mining,Graph Neural Networ
Classifier: Development Status :: 3 - Alpha
Classifier: Intended Audience :: Developers
Classifier: Intended Audience :: Financial and Insurance Industry
Classifier: Intended Audience :: Healthcare Industry
Classifier: Intended Audience :: Information Technology
Classifier: Intended Audience :: Manufacturing
Classifier: Intended Audience :: Science/Research
Classifier: Intended Audience :: Telecommunications Industry
Classifier: Intended Audience :: Other Audience
Classifier: Topic :: Scientific/Engineering :: Artificial Intelligence
Classifier: Topic :: Scientific/Engineering :: Information Analysis
Classifier: Topic :: Scientific/Engineering :: Visualization
Classifier: Topic :: Software Development :: Libraries :: Python Modules
Classifier: Topic :: Software Development :: Libraries :: Application Frameworks
Classifier: Topic :: Software Development :: Libraries :: Python Modules
Classifier: Topic :: Software Development :: User Interfaces
Classifier: Topic :: Software Development :: Widget Sets
Classifier: Topic :: Text Processing :: Linguistic
Classifier: Topic :: Text Processing :: Markup :: HTML
Classifier: Topic :: Text Processing :: Markup :: XML
Classifier: Topic :: Text Processing :: Markup :: Markdown
Classifier: Topic :: Utilities
Classifier: License :: Other/Proprietary License
Classifier: Operating System :: OS Independent
Classifier: Natural Language :: English
Classifier: Programming Language :: Python :: 3.9
Classifier: Programming Language :: Python :: 3.10
Classifier: Typing :: Typed
Requires-Python: >=3.10, <3.11
License-File: LICENCE
Requires-Dist: aiofiles ==23.2.1
Requires-Dist: aiohttp ==3.9.4
Requires-Dist: attrs ==23.1.0
Requires-Dist: azure-storage-blob ==12.19.0
Requires-Dist: beautifulsoup4 ==4.12.3
Requires-Dist: boto3 ==1.26.146
Requires-Dist: botocore ==1.29.146
Requires-Dist: bs4 ==0.0.1
Requires-Dist: cachetools ==5.3.3
Requires-Dist: coverage ==7.3.3
Requires-Dist: dropbox ==11.36.2
Requires-Dist: fastembed ==0.2.6
Requires-Dist: ffmpeg-python ==0.2.0
Requires-Dist: gensim ==4.3.2
Requires-Dist: gguf ==0.6.0
Requires-Dist: google-api-python-client ==2.105.0
Requires-Dist: google-cloud-storage ==2.14.0
Requires-Dist: hdbscan ==0.8.33
Requires-Dist: jira ==3.6.0
Requires-Dist: jmespath ==1.0.1
Requires-Dist: joblib ==1.2.0
Requires-Dist: json5 ==0.9.24
Requires-Dist: jsonmerge ==1.9.0
Requires-Dist: jsonschema ==4.17.3
Requires-Dist: kombu ==5.2.4
Requires-Dist: langchain ==0.1.11
Requires-Dist: langchain-community ==0.0.25
Requires-Dist: llama-cpp-python ==0.2.15
Requires-Dist: lxml ==4.9.2
Requires-Dist: moviepy ==1.0.3
Requires-Dist: newspaper3k ==0.2.8
Requires-Dist: newsapi-python ==0.2.7
Requires-Dist: nltk ==3.8.1
Requires-Dist: numpy ==1.24.3
Requires-Dist: openai ==1.13.3
Requires-Dist: openpyxl ==3.1.2
Requires-Dist: pandas ==2.1.4
Requires-Dist: pdfminer ==20191125
Requires-Dist: pdfplumber ==0.10.0
Requires-Dist: pillow ==10.3.0
Requires-Dist: prometheus-client ==0.17.1
Requires-Dist: psutil ==5.9.8
Requires-Dist: pybase64 ==1.3.1
Requires-Dist: pydantic ==2.6.4
Requires-Dist: pydub ==0.25.1
Requires-Dist: pyjwt ==2.4.0
Requires-Dist: pylint ==2.17.4
Requires-Dist: pymupdf ==1.24.0
Requires-Dist: pyshacl ==0.25.0
Requires-Dist: pytesseract ==0.3.10
Requires-Dist: pytextract ==2.0.1
Requires-Dist: python-dotenv ==1.0.0
Requires-Dist: python-docx ==1.1.0
Requires-Dist: python-pptx ==0.6.23
Requires-Dist: rdflib ==7.0.0
Requires-Dist: redis ==5.0.3
Requires-Dist: regex ==2023.5.5
Requires-Dist: requests ==2.31.0
Requires-Dist: requests-html ==0.10.0
Requires-Dist: slack-sdk ==3.26.1
Requires-Dist: spacy ==3.7.2
Requires-Dist: speechrecognition ==3.10.1
Requires-Dist: tika ==2.6.0
Requires-Dist: tensorflow ==2.14.0
Requires-Dist: transformers ==4.36.0
Requires-Dist: unidecode ==1.3.7
